heavy_celery/__init__.py
heavy_celery/admin.py
heavy_celery/apps.py
heavy_celery/base.py
heavy_celery/cron.py
heavy_celery/middlewares.py
heavy_celery/models.py
heavy_celery/storage.py
heavy_celery/tasks.py
heavy_celery/urls.py
heavy_celery/utils.py
heavy_celery/views.py
heavy_celery/migrations/0001_initial.py
heavy_celery/migrations/0002_auto_20170712_0625.py
heavy_celery/migrations/0003_auto_20190302_2256.py
heavy_celery/migrations/0004_auto_20190303_0128.py
heavy_celery/migrations/0005_delete_workerheartbeat.py
heavy_celery/migrations/__init__.py
heavy_celery/static/css/heavy_celery.css
heavy_celery/static/js/heavy_celery.js
heavy_celery/templates/heavy_celery/base.html
heavy_celery-0.3.0.dist-info/METADATA
heavy_celery-0.3.0.dist-info/RECORD
heavy_celery-0.3.0.dist-info/WHEEL
heavy_celery-0.3.0.dist-info/top_level.txt
